README.md
setup.cfg
setup.py
noyolajp_distributions/Binomialdistribution.py
noyolajp_distributions/Gaussiandistribution.py
noyolajp_distributions/Generaldistribution.py
noyolajp_distributions/__init__.py
noyolajp_distributions.egg-info/PKG-INFO
noyolajp_distributions.egg-info/SOURCES.txt
noyolajp_distributions.egg-info/dependency_links.txt
noyolajp_distributions.egg-info/not-zip-safe
noyolajp_distributions.egg-info/top_level.txt